	<!-- showSongstoAll -->

	<screen name="Songs.to" position="0,0" size="1280,720" flags="wfNoBorder">
	
	<!-- Background -->
	<eLabel position="0,0" zPosition="-5" size="1280,720" backgroundColor="XionLightBackground"/>
		<eLabel position="75,85" size="1125,552" zPosition="-4" backgroundColor="XionLightBackground"/>
	<ePixmap position="0,0" size="1280,720" zPosition="-3" pixmap="~/XionLight/images/mp_bg_detail.png" alphatest="blend" />

	<!-- Datum/Uhrzeit -->
	<widget source="global.CurrentTime" render="Label" position="1120,122" size="100,25" backgroundColor="#00000000" zPosition="3" font="mediaportal; 16" valign="center" halign="left" transparent="1" foregroundColor="#00ffffff" >
		<convert type="ClockToText">Format:%H:%M:%S</convert>
	</widget>
	<widget source="global.CurrentTime" render="Label" position="815,122" size="300,25" backgroundColor="#00000000" zPosition="3" font="mediaportal; 16" valign="center" halign="right" transparent="1" foregroundColor="#00ffffff" >
		<convert type="ClockToText">Format:%A %d.%B %Y</convert>
	</widget>
	
	<!-- select screen -->
	<widget name="title" position="100,85" size="650,30" zPosition="1" transparent="1" font="mediaportal; 26" valign="center" halign="left" backgroundColor="#00000000" foregroundColor="#00ffffff" />
	<eLabel text="Songliste" position="100,125" size="750,20" zPosition="1" transparent="1" font="mediaportal; 20" valign="center" halign="left" backgroundColor="#00000000" foregroundColor="#00ffffff" />

    <widget name="liste"  position="485,166" size="697,390" backgroundColor="#00000000" zPosition="1" scrollbarMode="showOnDemand" transparent="1" foregroundColorSelected="XionLightSelFont" foregroundColor="#00ffffff" />
    
	<eLabel text="Song: " position="112,180" size="340,25" backgroundColor="#00000000" transparent="1" zPosition="1" font="mediaportal; 20" valign="center" halign="left" foregroundColor="#00ffffff" />
    <widget name="songtitle" position="112,210" size="340,20" backgroundColor="#00000000" transparent="1" zPosition="1" font="mediaportal; 18" valign="center" halign="left" foregroundColor="#00ffffff" />
    <eLabel text="Interpret: " position="112,240" size="340,25" backgroundColor="#00000000" transparent="1" zPosition="1" font="mediaportal; 20" valign="center" halign="left" foregroundColor="#00ffffff" />
    <widget name="artist" position="112,270" size="340,20" backgroundColor="#00000000" transparent="1" zPosition="1" font="mediaportal; 18" valign="center" halign="left" foregroundColor="#00ffffff" />
	<eLabel text="Playmode:" position="112,300" size="340,25" backgroundColor="#0000000" transparent="1" zPosition="1" font="mediaportal;20" valign="center" halign="left" foregroundColor="#00ffffff" />
    <widget name="album" position="112,330" size="340,25" backgroundColor="#00000000" transparent="1" zPosition="1" font="mediaportal;18" valign="center" halign="left" foregroundColor="#00ffffff" />
	
	<widget source="session.CurrentService" render="Progress" position="112,535" size="341,12"  zPosition="5" backgroundColor="#00323232" foregroundColor="#00ffffff" borderWidth="1" borderColor="#00000000" transparent="0">
      <convert type="ServicePosition">Position</convert>
    </widget>
    <widget source="session.CurrentService" render="Label" position="112,515" size="341,25"  zPosition="5" backgroundColor="#00000000" transparent="1" font="mediaportal; 16" valign="center" halign="left" foregroundColor="#00ffffff">
      <convert type="ServicePosition">Position</convert>
    </widget>
    <widget source="session.CurrentService" render="Label" position="112,515" size="341,25"  zPosition="5" backgroundColor="#00000000" transparent="1" font="mediaportal; 16" valign="center" halign="center" foregroundColor="#00ffffff">
      <convert type="ServicePosition">Remaining</convert>
    </widget>
	<widget source="session.CurrentService" render="Label" position="112,515" size="341,25"  zPosition="5" backgroundColor="#00000000" transparent="1" font="mediaportal; 16" valign="center" halign="right" foregroundColor="#00ffffff">
      <convert type="ServicePosition">Length</convert>
    </widget>
	
	<widget name="coverArt" pixmap="~/XionLight/images/nc_musik.png" position="112,370" size="160,100" zPosition="4" backgroundColor="#00000000" transparent="1" borderWidth="2" borderColor="#0000000" alphatest="blend" />
	
	<!-- Buttons -->
    <widget name="F1" position="75,673" size="120,20" transparent="1" font="mediaportal; 18" backgroundColor="#00000000" foregroundColor="#00ffffff" valign="center" halign="left" zPosition="6" />
    <widget name="F2" position="222,673" size="120,20" transparent="1" font="mediaportal; 18" backgroundColor="#00000000" foregroundColor="#00ffffff" valign="center" halign="left" zPosition="6" />
    <widget name="F3" position="375,673" size="120,20" transparent="1" font="mediaportal; 18" backgroundColor="#00000000" foregroundColor="#00ffffff" valign="center" halign="left" zPosition="6" />
    <widget name="F4" position="530,673" size="120,20" transparent="1" font="mediaportal; 18" backgroundColor="#00000000" foregroundColor="#00ffffff" valign="center" halign="left" zPosition="6" /> 

	<eLabel text=" Playlist " position="220,673" size="120,20" transparent="1" font="mediaportal; 18" backgroundColor="#00000000" foregroundColor="#00ffffff" valign="center" halign="left" zPosition="6" />
    <!--eLabel text=" Playmode " position="365,670" size="120,20" transparent="1" font="mediaportal; 18" backgroundColor="#00000000" foregroundColor="#00ffffff" valign="center" halign="left" zPosition="6" /-->	
	
	<eLabel text=" " position="735,673" size="120,20" transparent="1" font="mediaportal; 18" backgroundColor="#00000000" foregroundColor="#00ffffff" valign="center" halign="left" zPosition="6" />	
    <eLabel text=" " position="860,673" size="120,20" transparent="1" font="mediaportal; 18" backgroundColor="#00000000" foregroundColor="#00ffffff" valign="center" halign="left" zPosition="6" />
    <eLabel text=" CH+ " position="985,673" size="120,20" transparent="1" font="mediaportal; 18" backgroundColor="#00000000" foregroundColor="#00ffffff" valign="center" halign="left" zPosition="6" />
    <eLabel text=" CH- " position="1110,673" size="120,20" transparent="1" font="mediaportal; 18" backgroundColor="#00000000" foregroundColor="#00ffffff" valign="center" halign="left" zPosition="6" />
	
	<ePixmap position="40,665" size="32,32" zPosition="4" pixmap="~/XionLight/images/nav_red.png" alphatest="on" />
	<ePixmap position="185,665" size="32,32" zPosition="4" pixmap="~/XionLight/images/nav_green.png" alphatest="on" />
	<ePixmap position="340,665" size="32,32" zPosition="4" pixmap="~/XionLight/images/nav_yellow.png" alphatest="on" />
	<ePixmap position="495,665" size="32,32" zPosition="4" pixmap="~/XionLight/images/nav_blue.png" alphatest="on"/>

	<ePixmap position="700,665" size="32,32" zPosition="4" pixmap="~/XionLight/images/nav_grey.png" alphatest="on" />
	<ePixmap position="825,665" size="32,32" zPosition="4" pixmap="~/XionLight/images/nav_grey.png" alphatest="on" />
	<ePixmap position="950,665" size="32,32" zPosition="4" pixmap="~/XionLight/images/nav_grey.png" alphatest="on" />
	<ePixmap position="1075,665" size="32,32" zPosition="4" pixmap="~/XionLight/images/nav_grey.png" alphatest="on" />	
	</screen>	